jinja2_workarounds/__init__.py
jinja2_workarounds-0.1.0.dist-info/WHEEL
jinja2_workarounds-0.1.0.dist-info/METADATA
jinja2_workarounds-0.1.0.dist-info/RECORD
