Metadata-Version: 2.1
Name: jinja2-workarounds
Version: 0.1.0
Summary: A jinja2 extension for includes with correct indentation
License: MIT
Author: Sascha Desch
Author-email: sascha.desch@hotmail.com
Requires-Python: >=3.7,<4.0
Classifier: License :: OSI Approved :: MIT License
Classifier: Programming Language :: Python :: 3
Classifier: Programming Language :: Python :: 3.10
Classifier: Programming Language :: Python :: 3.7
Classifier: Programming Language :: Python :: 3.8
Classifier: Programming Language :: Python :: 3.9
Requires-Dist: Jinja2 (>=3.0.3,<4.0.0)
